py3langid/__init__.py
py3langid/langid.py
py3langid/data/model.plzma
py3langid-0.3.0.dist-info/LICENSE
py3langid-0.3.0.dist-info/METADATA
py3langid-0.3.0.dist-info/WHEEL
py3langid-0.3.0.dist-info/entry_points.txt
py3langid-0.3.0.dist-info/top_level.txt
py3langid-0.3.0.dist-info/RECORD
