Metadata-Version: 2.1
Name: py3langid
Version: 0.3.0
Summary: Fork of the language identification tool langid.py, featuring a modernized codebase and faster execution times.
Author: Marco Lui
Author-email: Adrien Barbaresi <barbaresi@bbaw.de>
License: BSD
Project-URL: Homepage, https://github.com/adbar/py3langid
Project-URL: Blog, https://adrien.barbaresi.eu/blog/language-detection-langid-py-faster.html
Project-URL: Tracker, https://github.com/adbar/py3langid/issues
Keywords: language detection,language identification,langid,langid.py
Classifier: Development Status :: 5 - Production/Stable
Classifier: Environment :: Console
Classifier: Intended Audience :: Developers
Classifier: Intended Audience :: Information Technology
Classifier: Intended Audience :: Science/Research
Classifier: License :: OSI Approved :: BSD License
Classifier: Operating System :: MacOS :: MacOS X
Classifier: Operating System :: Microsoft :: Windows
Classifier: Operating System :: POSIX :: Linux
Classifier: Programming Language :: Python
Classifier: Programming Language :: Python :: 3
Classifier: Programming Language :: Python :: 3.8
Classifier: Programming Language :: Python :: 3.9
Classifier: Programming Language :: Python :: 3.10
Classifier: Programming Language :: Python :: 3.11
Classifier: Programming Language :: Python :: 3.12
Classifier: Programming Language :: Python :: 3.13
Classifier: Topic :: Scientific/Engineering :: Artificial Intelligence
Classifier: Topic :: Text Processing :: Linguistic
Requires-Python: >=3.8
License-File: LICENSE
Requires-Dist: numpy>=2.0.0; python_version >= "3.9"
Requires-Dist: numpy>=1.24.3; python_version == "3.8"
Provides-Extra: dev
Requires-Dist: pytest; extra == "dev"
Requires-Dist: pytest-cov; extra == "dev"
